hibp/__init__.py
hibp/constants.py
hibp/hibp.py
hibp_zetsumeishi-0.1.3.dist-info/LICENSE
hibp_zetsumeishi-0.1.3.dist-info/METADATA
hibp_zetsumeishi-0.1.3.dist-info/WHEEL
hibp_zetsumeishi-0.1.3.dist-info/top_level.txt
hibp_zetsumeishi-0.1.3.dist-info/RECORD
