Metadata-Version: 2.1
Name: hibp-zetsumeishi
Version: 0.1.3
Summary: Python interface to communicate with HaveIBeenPwned.com
Home-page: https://github.com/zetsumeishi/hibp
Author: zetsumeishi
Author-email: olivier.loustaunau@gmail.com
License: UNKNOWN
Platform: UNKNOWN
Classifier: Programming Language :: Python :: 3
Classifier: License :: OSI Approved :: MIT License
Classifier: Operating System :: OS Independent
Requires-Python: >=3.6
Requires-Dist: requests
